{
  "schemaVersion": 1,
  "id": "modal_verbs_a2_tier7_slot-substitution",
  "kind": "drill",
  "drillVersion": "v4",
  "workspace": "de",
  "language": "de",
  "level": "A2",
  "title": "Modal Verbs: A2 (Tier 7) - Slot",
  "shortTitle": "Modal Verbs A2 Slot",
  "subtitle": "Tier 7 - slot substitution - Practice modal verbs (können, m",
  "estimatedMinutes": 5,
  "mechanicId": "modal_verbs",
  "mechanicLabel": "Modal Verbs",
  "loopType": "slot_substitution",
  "difficultyTier": 7,
  "variationSlots": [
    "subject",
    "verb",
    "object",
    "modifier",
    "time"
  ],
  "sessionPlan": {
    "version": 1,
    "steps": [
      {
        "id": "step-1",
        "title": "Step 1",
        "promptIds": [
          "prompt-001",
          "prompt-002",
          "prompt-003",
          "prompt-004",
          "prompt-005",
          "prompt-006"
        ],
        "title_i18n": {
          "en": "Step 1"
        }
      },
      {
        "id": "step-2",
        "title": "Step 2",
        "promptIds": [
          "prompt-007",
          "prompt-008",
          "prompt-009",
          "prompt-010",
          "prompt-011",
          "prompt-012"
        ],
        "title_i18n": {
          "en": "Step 2"
        }
      },
      {
        "id": "step-3",
        "title": "Step 3",
        "promptIds": [
          "prompt-013",
          "prompt-014",
          "prompt-015",
          "prompt-016",
          "prompt-017",
          "prompt-018"
        ],
        "title_i18n": {
          "en": "Step 3"
        }
      }
    ]
  },
  "prompts": [
    {
      "id": "prompt-001",
      "text": "am Wochenende willst du dort das sehen.",
      "intent": "practice",
      "gloss_en": "I am practicing this grammar mechanic.",
      "natural_en": "am Wochenende willst du dort das sehen.",
      "slotsChanged": [
        "subject",
        "verb",
        "object",
        "time",
        "location"
      ],
      "slots": {
        "subject": [
          "Du"
        ],
        "verb": [
          "willst"
        ],
        "object": [
          "das"
        ],
        "time": [
          "am Wochenende"
        ],
        "location": [
          "dort"
        ],
        "infinitive": [
          "sehen"
        ]
      },
      "audioUrl": "/v1/audio/modal_verbs_A2_tier7/prompt-001.mp3"
    },
    {
      "id": "prompt-002",
      "text": "morgen musst du hier ins Kino hören.",
      "intent": "practice",
      "gloss_en": "I am practicing this grammar mechanic.",
      "natural_en": "morgen musst du hier ins Kino hören.",
      "slotsChanged": [
        "subject",
        "verb",
        "time",
        "location",
        "object"
      ],
      "slots": {
        "subject": [
          "Du"
        ],
        "verb": [
          "musst"
        ],
        "object": [
          "ins Kino"
        ],
        "time": [
          "morgen"
        ],
        "location": [
          "hier"
        ],
        "infinitive": [
          "hören"
        ]
      },
      "audioUrl": "/v1/audio/modal_verbs_A2_tier7/prompt-002.mp3"
    },
    {
      "id": "prompt-003",
      "text": "nächste Woche willst du bei Freunden den schlafen.",
      "intent": "practice",
      "gloss_en": "I am practicing this grammar mechanic.",
      "natural_en": "nächste Woche willst du bei Freunden den schlafen.",
      "slotsChanged": [
        "subject",
        "verb",
        "object",
        "time",
        "location"
      ],
      "slots": {
        "subject": [
          "Du"
        ],
        "verb": [
          "willst"
        ],
        "object": [
          "den"
        ],
        "time": [
          "nächste Woche"
        ],
        "location": [
          "bei Freunden"
        ],
        "infinitive": [
          "schlafen"
        ]
      },
      "audioUrl": "/v1/audio/modal_verbs_A2_tier7/prompt-003.mp3"
    },
    {
      "id": "prompt-004",
      "text": "bald möchten wir bei Freunden kommen.",
      "intent": "practice",
      "gloss_en": "I am practicing this grammar mechanic.",
      "natural_en": "bald möchten wir bei Freunden kommen.",
      "slotsChanged": [
        "subject",
        "verb",
        "time",
        "location"
      ],
      "slots": {
        "subject": [
          "Wir"
        ],
        "verb": [
          "möchten"
        ],
        "time": [
          "bald"
        ],
        "location": [
          "bei Freunden"
        ],
        "infinitive": [
          "kommen"
        ]
      },
      "audioUrl": "/v1/audio/modal_verbs_A2_tier7/prompt-004.mp3"
    },
    {
      "id": "prompt-005",
      "text": "morgen sollen wir zu Hause eine arbeiten.",
      "intent": "practice",
      "gloss_en": "I am practicing this grammar mechanic.",
      "natural_en": "morgen sollen wir zu Hause eine arbeiten.",
      "slotsChanged": [
        "subject",
        "verb",
        "object",
        "time",
        "location"
      ],
      "slots": {
        "subject": [
          "Wir"
        ],
        "verb": [
          "sollen"
        ],
        "object": [
          "eine"
        ],
        "time": [
          "morgen"
        ],
        "location": [
          "zu Hause"
        ],
        "infinitive": [
          "arbeiten"
        ]
      },
      "audioUrl": "/v1/audio/modal_verbs_A2_tier7/prompt-005.mp3"
    },
    {
      "id": "prompt-006",
      "text": "jetzt wollen wir zu Hause machen.",
      "intent": "practice",
      "gloss_en": "I am practicing this grammar mechanic.",
      "natural_en": "jetzt wollen wir zu Hause machen.",
      "slotsChanged": [
        "subject",
        "verb",
        "time",
        "location"
      ],
      "slots": {
        "subject": [
          "Wir"
        ],
        "verb": [
          "wollen"
        ],
        "time": [
          "jetzt"
        ],
        "location": [
          "zu Hause"
        ],
        "infinitive": [
          "machen"
        ]
      },
      "audioUrl": "/v1/audio/modal_verbs_A2_tier7/prompt-006.mp3"
    },
    {
      "id": "prompt-007",
      "text": "später sollt ihr dort zur Arbeit essen.",
      "intent": "practice",
      "gloss_en": "I am practicing this grammar mechanic.",
      "natural_en": "später sollt ihr dort zur Arbeit essen.",
      "slotsChanged": [
        "subject",
        "verb",
        "object",
        "time",
        "location"
      ],
      "slots": {
        "subject": [
          "Ihr"
        ],
        "verb": [
          "sollt"
        ],
        "object": [
          "zur Arbeit"
        ],
        "time": [
          "später"
        ],
        "location": [
          "dort"
        ],
        "infinitive": [
          "essen"
        ]
      },
      "audioUrl": "/v1/audio/modal_verbs_A2_tier7/prompt-007.mp3"
    },
    {
      "id": "prompt-008",
      "text": "bald sollt ihr in der Stadt kaufen.",
      "intent": "practice",
      "gloss_en": "I am practicing this grammar mechanic.",
      "natural_en": "bald sollt ihr in der Stadt kaufen.",
      "slotsChanged": [
        "subject",
        "verb",
        "time",
        "location"
      ],
      "slots": {
        "subject": [
          "Ihr"
        ],
        "verb": [
          "sollt"
        ],
        "time": [
          "bald"
        ],
        "location": [
          "in der Stadt"
        ],
        "infinitive": [
          "kaufen"
        ]
      },
      "audioUrl": "/v1/audio/modal_verbs_A2_tier7/prompt-008.mp3"
    },
    {
      "id": "prompt-009",
      "text": "am Wochenende wollt ihr in der Stadt die spielen.",
      "intent": "practice",
      "gloss_en": "I am practicing this grammar mechanic.",
      "natural_en": "am Wochenende wollt ihr in der Stadt die spielen.",
      "slotsChanged": [
        "subject",
        "verb",
        "object",
        "time",
        "location"
      ],
      "slots": {
        "subject": [
          "Ihr"
        ],
        "verb": [
          "wollt"
        ],
        "object": [
          "die"
        ],
        "time": [
          "am Wochenende"
        ],
        "location": [
          "in der Stadt"
        ],
        "infinitive": [
          "spielen"
        ]
      },
      "audioUrl": "/v1/audio/modal_verbs_A2_tier7/prompt-009.mp3"
    },
    {
      "id": "prompt-010",
      "text": "heute möchte er hier trinken.",
      "intent": "practice",
      "gloss_en": "I am practicing this grammar mechanic.",
      "natural_en": "heute möchte er hier trinken.",
      "slotsChanged": [
        "subject",
        "verb",
        "time",
        "location"
      ],
      "slots": {
        "subject": [
          "Er"
        ],
        "verb": [
          "möchte"
        ],
        "time": [
          "heute"
        ],
        "location": [
          "hier"
        ],
        "infinitive": [
          "trinken"
        ]
      },
      "audioUrl": "/v1/audio/modal_verbs_A2_tier7/prompt-010.mp3"
    },
    {
      "id": "prompt-011",
      "text": "später möchte er dort nach Hause gehen.",
      "intent": "practice",
      "gloss_en": "I am practicing this grammar mechanic.",
      "natural_en": "später möchte er dort nach Hause gehen.",
      "slotsChanged": [
        "subject",
        "verb",
        "object",
        "time",
        "location"
      ],
      "slots": {
        "subject": [
          "Er"
        ],
        "verb": [
          "möchte"
        ],
        "object": [
          "nach Hause"
        ],
        "time": [
          "später"
        ],
        "location": [
          "dort"
        ],
        "infinitive": [
          "gehen"
        ]
      },
      "audioUrl": "/v1/audio/modal_verbs_A2_tier7/prompt-011.mp3"
    },
    {
      "id": "prompt-012",
      "text": "nächste Woche kann er hier sehen.",
      "intent": "practice",
      "gloss_en": "I am practicing this grammar mechanic.",
      "natural_en": "nächste Woche kann er hier sehen.",
      "slotsChanged": [
        "subject",
        "verb",
        "time",
        "location"
      ],
      "slots": {
        "subject": [
          "Er"
        ],
        "verb": [
          "kann"
        ],
        "time": [
          "nächste Woche"
        ],
        "location": [
          "hier"
        ],
        "infinitive": [
          "sehen"
        ]
      },
      "audioUrl": "/v1/audio/modal_verbs_A2_tier7/prompt-012.mp3"
    },
    {
      "id": "prompt-013",
      "text": "nächste Woche möchte Sie in der Stadt das hören.",
      "intent": "practice",
      "gloss_en": "I am practicing this grammar mechanic.",
      "natural_en": "nächste Woche möchte Sie in der Stadt das hören.",
      "slotsChanged": [
        "subject",
        "verb",
        "object",
        "time",
        "location"
      ],
      "slots": {
        "subject": [
          "Sie"
        ],
        "verb": [
          "möchte"
        ],
        "object": [
          "das"
        ],
        "time": [
          "nächste Woche"
        ],
        "location": [
          "in der Stadt"
        ],
        "infinitive": [
          "hören"
        ]
      },
      "audioUrl": "/v1/audio/modal_verbs_A2_tier7/prompt-013.mp3"
    },
    {
      "id": "prompt-014",
      "text": "nächste Woche will Sie hier lernen.",
      "intent": "practice",
      "gloss_en": "I am practicing this grammar mechanic.",
      "natural_en": "nächste Woche will Sie hier lernen.",
      "slotsChanged": [
        "subject",
        "verb",
        "time",
        "location"
      ],
      "slots": {
        "subject": [
          "Sie"
        ],
        "verb": [
          "will"
        ],
        "time": [
          "nächste Woche"
        ],
        "location": [
          "hier"
        ],
        "infinitive": [
          "lernen"
        ]
      },
      "audioUrl": "/v1/audio/modal_verbs_A2_tier7/prompt-014.mp3"
    },
    {
      "id": "prompt-015",
      "text": "am Wochenende soll Sie in der Stadt ins Kino schlafen.",
      "intent": "practice",
      "gloss_en": "I am practicing this grammar mechanic.",
      "natural_en": "am Wochenende soll Sie in der Stadt ins Kino schlafen.",
      "slotsChanged": [
        "subject",
        "verb",
        "object",
        "time",
        "location"
      ],
      "slots": {
        "subject": [
          "Sie"
        ],
        "verb": [
          "soll"
        ],
        "object": [
          "ins Kino"
        ],
        "time": [
          "am Wochenende"
        ],
        "location": [
          "in der Stadt"
        ],
        "infinitive": [
          "schlafen"
        ]
      },
      "audioUrl": "/v1/audio/modal_verbs_A2_tier7/prompt-015.mp3"
    },
    {
      "id": "prompt-016",
      "text": "bald möchte ich im Büro kommen.",
      "intent": "practice",
      "gloss_en": "I am practicing this grammar mechanic.",
      "natural_en": "bald möchte ich im Büro kommen.",
      "slotsChanged": [
        "subject",
        "verb",
        "time",
        "location"
      ],
      "slots": {
        "subject": [
          "Ich"
        ],
        "verb": [
          "möchte"
        ],
        "time": [
          "bald"
        ],
        "location": [
          "im Büro"
        ],
        "infinitive": [
          "kommen"
        ]
      },
      "audioUrl": "/v1/audio/modal_verbs_A2_tier7/prompt-016.mp3"
    },
    {
      "id": "prompt-017",
      "text": "nächste Woche möchte ich zu Hause die arbeiten.",
      "intent": "practice",
      "gloss_en": "I am practicing this grammar mechanic.",
      "natural_en": "nächste Woche möchte ich zu Hause die arbeiten.",
      "slotsChanged": [
        "subject",
        "verb",
        "object",
        "time",
        "location"
      ],
      "slots": {
        "subject": [
          "Ich"
        ],
        "verb": [
          "möchte"
        ],
        "object": [
          "die"
        ],
        "time": [
          "nächste Woche"
        ],
        "location": [
          "zu Hause"
        ],
        "infinitive": [
          "arbeiten"
        ]
      },
      "audioUrl": "/v1/audio/modal_verbs_A2_tier7/prompt-017.mp3"
    },
    {
      "id": "prompt-018",
      "text": "später will ich zu Hause machen.",
      "intent": "practice",
      "gloss_en": "I am practicing this grammar mechanic.",
      "natural_en": "später will ich zu Hause machen.",
      "slotsChanged": [
        "subject",
        "verb",
        "time",
        "location"
      ],
      "slots": {
        "subject": [
          "Ich"
        ],
        "verb": [
          "will"
        ],
        "time": [
          "später"
        ],
        "location": [
          "zu Hause"
        ],
        "infinitive": [
          "machen"
        ]
      },
      "audioUrl": "/v1/audio/modal_verbs_A2_tier7/prompt-018.mp3"
    }
  ],
  "analytics": {
    "version": 1,
    "mechanicId": "modal_verbs",
    "loopType": "slot_substitution",
    "targetStructures": [
      "modal_verb_infinitive",
      "modal_verb_requests",
      "modal_verb_ability"
    ],
    "variationSlots": [
      "subject",
      "verb"
    ],
    "coverage": {
      "verbs": [
        "willst",
        "musst",
        "möchten",
        "sollen",
        "wollen",
        "sollt",
        "wollt",
        "möchte",
        "kann",
        "will",
        "soll"
      ],
      "subjects": [
        "Du",
        "Wir",
        "Ihr",
        "Er",
        "Sie",
        "Ich"
      ],
      "patterns": [
        "modal_verb_infinitive",
        "modal_verb_requests",
        "modal_verb_ability"
      ]
    },
    "difficultyTier": 7,
    "recommendedReps": 4,
    "estPromptCount": 18,
    "timeboxMinutes": 5,
    "qualitySignals": {
      "tokenHitsCount": 18,
      "multiSlotRate": 1,
      "uniqueVerbCount": 11,
      "uniqueSubjectCount": 6,
      "trapPairCount": 0,
      "bannedPhraseCheckPassed": true
    }
  },
  "provenance": {
    "source": "template",
    "sourceRef": "mechanics/modal_verbs",
    "extractorVersion": "v4.0.0",
    "generatedAt": "2026-01-04T06:49:17.664Z"
  },
  "review": {
    "status": "needs_review"
  },
  "title_i18n": {
    "en": "Modal Verbs: A2 (Tier 7) - Slot"
  },
  "shortTitle_i18n": {
    "en": "Modal Verbs A2 Slot"
  },
  "subtitle_i18n": {
    "en": "Tier 7 - slot substitution - Practice modal verbs (können, m"
  },
  "contentId": "de:drill:modal_verbs_a2_tier7_slot-substitution",
  "contentHash": "7cca62570b198051d56d2c205d13087284760fe11f2d0547da69926f7b2bf0e6",
  "revisionId": "7cca62570b19"
}
