{
  "schemaVersion": 1,
  "id": "modal_verbs_b1_tier1_pattern-switch",
  "kind": "drill",
  "drillVersion": "v4",
  "workspace": "de",
  "language": "de",
  "level": "B1",
  "title": "Modal Verbs: B1 (Tier 1) - Pattern",
  "shortTitle": "Modal Verbs B1 Pattern",
  "subtitle": "Tier 1 - pattern switch - Practice modal verbs (können, müss",
  "estimatedMinutes": 3,
  "mechanicId": "modal_verbs",
  "mechanicLabel": "Modal Verbs",
  "loopType": "pattern_switch",
  "difficultyTier": 1,
  "variationSlots": [
    "subject",
    "verb",
    "object",
    "modifier",
    "time"
  ],
  "sessionPlan": {
    "version": 1,
    "steps": [
      {
        "id": "pattern-1",
        "title": "Pattern 1: Basic Forms",
        "promptIds": [
          "prompt-001",
          "prompt-002"
        ],
        "title_i18n": {
          "en": "Pattern 1: Basic Forms"
        }
      },
      {
        "id": "pattern-2",
        "title": "Pattern 2: Extended Forms",
        "promptIds": [
          "prompt-003",
          "prompt-004"
        ],
        "title_i18n": {
          "en": "Pattern 2: Extended Forms"
        }
      },
      {
        "id": "pattern-3",
        "title": "Pattern 3: Complex Forms",
        "promptIds": [
          "prompt-005",
          "prompt-006"
        ],
        "title_i18n": {
          "en": "Pattern 3: Complex Forms"
        }
      }
    ]
  },
  "prompts": [
    {
      "id": "prompt-001",
      "text": "Er muss wirklich die kaufen.",
      "intent": "practice",
      "gloss_en": "I am practicing this grammar mechanic.",
      "natural_en": "Er muss wirklich die kaufen.",
      "slotsChanged": [
        "subject",
        "verb",
        "object",
        "modifier"
      ],
      "slots": {
        "subject": [
          "Er"
        ],
        "verb": [
          "muss"
        ],
        "object": [
          "die"
        ],
        "modifier": [
          "wirklich"
        ],
        "infinitive": [
          "kaufen"
        ]
      },
      "audioUrl": "/v1/audio/modal_verbs_B1_tier1/prompt-001.mp3"
    },
    {
      "id": "prompt-002",
      "text": "Du sollst vielleicht Deutsch gehen.",
      "intent": "practice",
      "gloss_en": "I am practicing this grammar mechanic.",
      "natural_en": "Du sollst vielleicht Deutsch gehen.",
      "slotsChanged": [
        "subject",
        "verb",
        "object",
        "modifier"
      ],
      "slots": {
        "subject": [
          "Du"
        ],
        "verb": [
          "sollst"
        ],
        "object": [
          "Deutsch"
        ],
        "modifier": [
          "vielleicht"
        ],
        "infinitive": [
          "gehen"
        ]
      },
      "audioUrl": "/v1/audio/modal_verbs_B1_tier1/prompt-002.mp3"
    },
    {
      "id": "prompt-003",
      "text": "später wollen wir eine hören.",
      "intent": "practice",
      "gloss_en": "I am practicing this grammar mechanic.",
      "natural_en": "später wollen wir eine hören.",
      "slotsChanged": [
        "time",
        "subject",
        "verb",
        "object"
      ],
      "slots": {
        "subject": [
          "Wir"
        ],
        "verb": [
          "wollen"
        ],
        "object": [
          "eine"
        ],
        "time": [
          "später"
        ],
        "infinitive": [
          "hören"
        ]
      },
      "audioUrl": "/v1/audio/modal_verbs_B1_tier1/prompt-003.mp3"
    },
    {
      "id": "prompt-004",
      "text": "Sie kann zur Arbeit spielen.",
      "intent": "practice",
      "gloss_en": "I am practicing this grammar mechanic.",
      "natural_en": "Sie kann zur Arbeit spielen.",
      "slotsChanged": [
        "subject",
        "verb",
        "object"
      ],
      "slots": {
        "subject": [
          "Sie"
        ],
        "verb": [
          "kann"
        ],
        "object": [
          "zur Arbeit"
        ],
        "infinitive": [
          "spielen"
        ]
      },
      "audioUrl": "/v1/audio/modal_verbs_B1_tier1/prompt-004.mp3"
    },
    {
      "id": "prompt-005",
      "text": "Ihr möchtet doch einen trinken.",
      "intent": "practice",
      "gloss_en": "I am practicing this grammar mechanic.",
      "natural_en": "Ihr möchtet doch einen trinken.",
      "slotsChanged": [
        "subject",
        "verb",
        "object",
        "modifier"
      ],
      "slots": {
        "subject": [
          "Ihr"
        ],
        "verb": [
          "möchtet"
        ],
        "object": [
          "einen"
        ],
        "modifier": [
          "doch"
        ],
        "infinitive": [
          "trinken"
        ]
      },
      "audioUrl": "/v1/audio/modal_verbs_B1_tier1/prompt-005.mp3"
    },
    {
      "id": "prompt-006",
      "text": "nächste Woche kann ich lernen.",
      "intent": "practice",
      "gloss_en": "I am practicing this grammar mechanic.",
      "natural_en": "nächste Woche kann ich lernen.",
      "slotsChanged": [
        "time",
        "subject",
        "verb"
      ],
      "slots": {
        "subject": [
          "Ich"
        ],
        "verb": [
          "kann"
        ],
        "time": [
          "nächste Woche"
        ],
        "infinitive": [
          "lernen"
        ]
      },
      "audioUrl": "/v1/audio/modal_verbs_B1_tier1/prompt-006.mp3"
    }
  ],
  "analytics": {
    "version": 1,
    "mechanicId": "modal_verbs",
    "loopType": "pattern_switch",
    "targetStructures": [
      "modal_verb_infinitive",
      "modal_verb_requests",
      "modal_verb_ability"
    ],
    "variationSlots": [
      "subject",
      "verb"
    ],
    "coverage": {
      "verbs": [
        "muss",
        "sollst",
        "wollen",
        "kann",
        "möchtet"
      ],
      "subjects": [
        "Er",
        "Du",
        "Wir",
        "Sie",
        "Ihr",
        "Ich"
      ],
      "patterns": [
        "modal_verb_infinitive",
        "modal_verb_requests",
        "modal_verb_ability"
      ]
    },
    "difficultyTier": 1,
    "recommendedReps": 2,
    "estPromptCount": 6,
    "timeboxMinutes": 3,
    "qualitySignals": {
      "tokenHitsCount": 6,
      "multiSlotRate": 1,
      "uniqueVerbCount": 5,
      "uniqueSubjectCount": 6,
      "trapPairCount": 0,
      "bannedPhraseCheckPassed": true
    }
  },
  "provenance": {
    "source": "template",
    "sourceRef": "mechanics/modal_verbs",
    "extractorVersion": "v4.0.0",
    "generatedAt": "2026-01-04T06:49:17.665Z"
  },
  "review": {
    "status": "needs_review"
  },
  "title_i18n": {
    "en": "Modal Verbs: B1 (Tier 1) - Pattern"
  },
  "shortTitle_i18n": {
    "en": "Modal Verbs B1 Pattern"
  },
  "subtitle_i18n": {
    "en": "Tier 1 - pattern switch - Practice modal verbs (können, müss"
  },
  "contentId": "de:drill:modal_verbs_b1_tier1_pattern-switch",
  "contentHash": "a57ecb726df1f007282b8291772c82e3617e15f182881fd4305bfc38280814a5",
  "revisionId": "a57ecb726df1"
}
