{
  "schemaVersion": 1,
  "id": "modal_verbs_a1_tier3_pattern-switch",
  "kind": "drill",
  "drillVersion": "v4",
  "workspace": "de",
  "language": "de",
  "level": "A1",
  "title": "Modal Verbs: A1 (Tier 3) - Pattern",
  "shortTitle": "Modal Verbs A1 Pattern",
  "subtitle": "Tier 3 - pattern switch - Master modal verb patterns (können",
  "estimatedMinutes": 5,
  "mechanicId": "modal_verbs",
  "mechanicLabel": "Modal Verbs",
  "loopType": "pattern_switch",
  "difficultyTier": 3,
  "variationSlots": [
    "subject",
    "verb",
    "object",
    "modifier",
    "time"
  ],
  "sessionPlan": {
    "version": 1,
    "steps": [
      {
        "id": "pattern-1",
        "title": "Pattern 1: Basic Forms",
        "promptIds": [
          "prompt-001",
          "prompt-002"
        ],
        "title_i18n": {
          "en": "Pattern 1: Basic Forms"
        }
      },
      {
        "id": "pattern-2",
        "title": "Pattern 2: Extended Forms",
        "promptIds": [
          "prompt-003",
          "prompt-004"
        ],
        "title_i18n": {
          "en": "Pattern 2: Extended Forms"
        }
      },
      {
        "id": "pattern-3",
        "title": "Pattern 3: Complex Forms",
        "promptIds": [
          "prompt-005",
          "prompt-006",
          "prompt-007",
          "prompt-008",
          "prompt-009",
          "prompt-010"
        ],
        "title_i18n": {
          "en": "Pattern 3: Complex Forms"
        }
      }
    ]
  },
  "prompts": [
    {
      "id": "prompt-001",
      "text": "am Wochenende möchte ich in der Stadt essen.",
      "intent": "practice",
      "gloss_en": "I am practicing this grammar mechanic.",
      "natural_en": "am Wochenende möchte ich in der Stadt essen.",
      "slotsChanged": [
        "subject",
        "verb",
        "time",
        "location"
      ],
      "slots": {
        "subject": [
          "Ich"
        ],
        "verb": [
          "möchte"
        ],
        "time": [
          "am Wochenende"
        ],
        "location": [
          "in der Stadt"
        ],
        "infinitive": [
          "essen"
        ]
      },
      "audioUrl": "/v1/audio/modal_verbs_A1_tier3/prompt-001.mp3"
    },
    {
      "id": "prompt-002",
      "text": "bald willst du dort eine kommen.",
      "intent": "practice",
      "gloss_en": "I am practicing this grammar mechanic.",
      "natural_en": "bald willst du dort eine kommen.",
      "slotsChanged": [
        "subject",
        "verb",
        "object",
        "time",
        "location"
      ],
      "slots": {
        "subject": [
          "Du"
        ],
        "verb": [
          "willst"
        ],
        "object": [
          "eine"
        ],
        "time": [
          "bald"
        ],
        "location": [
          "dort"
        ],
        "infinitive": [
          "kommen"
        ]
      },
      "audioUrl": "/v1/audio/modal_verbs_A1_tier3/prompt-002.mp3"
    },
    {
      "id": "prompt-003",
      "text": "später wollt ihr im Büro machen.",
      "intent": "practice",
      "gloss_en": "I am practicing this grammar mechanic.",
      "natural_en": "später wollt ihr im Büro machen.",
      "slotsChanged": [
        "time",
        "subject",
        "verb",
        "location"
      ],
      "slots": {
        "subject": [
          "Ihr"
        ],
        "verb": [
          "wollt"
        ],
        "time": [
          "später"
        ],
        "location": [
          "im Büro"
        ],
        "infinitive": [
          "machen"
        ]
      },
      "audioUrl": "/v1/audio/modal_verbs_A1_tier3/prompt-003.mp3"
    },
    {
      "id": "prompt-004",
      "text": "jetzt kann Sie zu Hause arbeiten.",
      "intent": "practice",
      "gloss_en": "I am practicing this grammar mechanic.",
      "natural_en": "jetzt kann Sie zu Hause arbeiten.",
      "slotsChanged": [
        "subject",
        "verb",
        "time",
        "location"
      ],
      "slots": {
        "subject": [
          "Sie"
        ],
        "verb": [
          "kann"
        ],
        "time": [
          "jetzt"
        ],
        "location": [
          "zu Hause"
        ],
        "infinitive": [
          "arbeiten"
        ]
      },
      "audioUrl": "/v1/audio/modal_verbs_A1_tier3/prompt-004.mp3"
    },
    {
      "id": "prompt-005",
      "text": "heute möchten wir bei Freunden das schlafen.",
      "intent": "practice",
      "gloss_en": "I am practicing this grammar mechanic.",
      "natural_en": "heute möchten wir bei Freunden das schlafen.",
      "slotsChanged": [
        "subject",
        "verb",
        "object",
        "time",
        "location"
      ],
      "slots": {
        "subject": [
          "Wir"
        ],
        "verb": [
          "möchten"
        ],
        "object": [
          "das"
        ],
        "time": [
          "heute"
        ],
        "location": [
          "bei Freunden"
        ],
        "infinitive": [
          "schlafen"
        ]
      },
      "audioUrl": "/v1/audio/modal_verbs_A1_tier3/prompt-005.mp3"
    },
    {
      "id": "prompt-006",
      "text": "heute will er hier den hören.",
      "intent": "practice",
      "gloss_en": "I am practicing this grammar mechanic.",
      "natural_en": "heute will er hier den hören.",
      "slotsChanged": [
        "time",
        "subject",
        "verb",
        "location",
        "object"
      ],
      "slots": {
        "subject": [
          "Er"
        ],
        "verb": [
          "will"
        ],
        "object": [
          "den"
        ],
        "time": [
          "heute"
        ],
        "location": [
          "hier"
        ],
        "infinitive": [
          "hören"
        ]
      },
      "audioUrl": "/v1/audio/modal_verbs_A1_tier3/prompt-006.mp3"
    },
    {
      "id": "prompt-007",
      "text": "am Wochenende soll ich zu Hause kaufen.",
      "intent": "practice",
      "gloss_en": "I am practicing this grammar mechanic.",
      "natural_en": "am Wochenende soll ich zu Hause kaufen.",
      "slotsChanged": [
        "subject",
        "verb",
        "time",
        "location"
      ],
      "slots": {
        "subject": [
          "Ich"
        ],
        "verb": [
          "soll"
        ],
        "time": [
          "am Wochenende"
        ],
        "location": [
          "zu Hause"
        ],
        "infinitive": [
          "kaufen"
        ]
      },
      "audioUrl": "/v1/audio/modal_verbs_A1_tier3/prompt-007.mp3"
    },
    {
      "id": "prompt-008",
      "text": "bald musst du zu Hause ins Kino lernen.",
      "intent": "practice",
      "gloss_en": "I am practicing this grammar mechanic.",
      "natural_en": "bald musst du zu Hause ins Kino lernen.",
      "slotsChanged": [
        "subject",
        "verb",
        "object",
        "time",
        "location"
      ],
      "slots": {
        "subject": [
          "Du"
        ],
        "verb": [
          "musst"
        ],
        "object": [
          "ins Kino"
        ],
        "time": [
          "bald"
        ],
        "location": [
          "zu Hause"
        ],
        "infinitive": [
          "lernen"
        ]
      },
      "audioUrl": "/v1/audio/modal_verbs_A1_tier3/prompt-008.mp3"
    },
    {
      "id": "prompt-009",
      "text": "später wollt ihr hier spielen.",
      "intent": "practice",
      "gloss_en": "I am practicing this grammar mechanic.",
      "natural_en": "später wollt ihr hier spielen.",
      "slotsChanged": [
        "time",
        "subject",
        "verb",
        "location"
      ],
      "slots": {
        "subject": [
          "Ihr"
        ],
        "verb": [
          "wollt"
        ],
        "time": [
          "später"
        ],
        "location": [
          "hier"
        ],
        "infinitive": [
          "spielen"
        ]
      },
      "audioUrl": "/v1/audio/modal_verbs_A1_tier3/prompt-009.mp3"
    },
    {
      "id": "prompt-010",
      "text": "bald kann Sie zu Hause trinken.",
      "intent": "practice",
      "gloss_en": "I am practicing this grammar mechanic.",
      "natural_en": "bald kann Sie zu Hause trinken.",
      "slotsChanged": [
        "subject",
        "verb",
        "time",
        "location"
      ],
      "slots": {
        "subject": [
          "Sie"
        ],
        "verb": [
          "kann"
        ],
        "time": [
          "bald"
        ],
        "location": [
          "zu Hause"
        ],
        "infinitive": [
          "trinken"
        ]
      },
      "audioUrl": "/v1/audio/modal_verbs_A1_tier3/prompt-010.mp3"
    }
  ],
  "analytics": {
    "version": 1,
    "mechanicId": "modal_verbs",
    "loopType": "pattern_switch",
    "targetStructures": [
      "modal_verb_infinitive",
      "modal_verb_requests",
      "modal_verb_ability"
    ],
    "variationSlots": [
      "subject",
      "verb"
    ],
    "coverage": {
      "verbs": [
        "möchte",
        "willst",
        "wollt",
        "kann",
        "möchten",
        "will",
        "soll",
        "musst"
      ],
      "subjects": [
        "Ich",
        "Du",
        "Ihr",
        "Sie",
        "Wir",
        "Er"
      ],
      "patterns": [
        "modal_verb_infinitive",
        "modal_verb_requests",
        "modal_verb_ability"
      ]
    },
    "difficultyTier": 3,
    "recommendedReps": 4,
    "estPromptCount": 10,
    "timeboxMinutes": 5,
    "qualitySignals": {
      "tokenHitsCount": 10,
      "multiSlotRate": 1,
      "uniqueVerbCount": 8,
      "uniqueSubjectCount": 6,
      "trapPairCount": 0,
      "bannedPhraseCheckPassed": true
    }
  },
  "provenance": {
    "source": "template",
    "sourceRef": "mechanics/modal_verbs",
    "extractorVersion": "v4.0.0",
    "generatedAt": "2026-01-03T09:52:17.351Z"
  },
  "review": {
    "status": "approved",
    "reviewer": "system",
    "reviewedAt": "2026-01-03T10:00:00.000Z"
  },
  "title_i18n": {
    "en": "Modal Verbs: A1 (Tier 3) - Pattern"
  },
  "shortTitle_i18n": {
    "en": "Modal Verbs A1 Pattern"
  },
  "subtitle_i18n": {
    "en": "Tier 3 - pattern switch - Master modal verb patterns (können"
  },
  "contentId": "de:drill:modal_verbs_a1_tier3_pattern-switch",
  "contentHash": "be398bb1a0e84b5718d15ac623473150b1d1154bd8519c0f9ac17afdb663862a",
  "revisionId": "be398bb1a0e8"
}
