{
  "version": "v1",
  "kind": "context",
  "total": 2,
  "pageSize": 20,
  "items": [
    {
      "id": "basic_greetings",
      "title": "Basic German Greetings",
      "level": "A1",
      "durationMinutes": 15,
      "entryUrl": "/v1/workspaces/de/packs/basic_greetings/pack.json"
    },
    {
      "id": "restaurant_conversations",
      "title": "Restaurant Conversations",
      "level": "A2",
      "durationMinutes": 20,
      "entryUrl": "/v1/workspaces/de/packs/restaurant_conversations/pack.json"
    }
  ],
  "nextPage": null
}

