{
  "schemaVersion": 1,
  "id": "modal_verbs_a1_tier4_pattern-switch",
  "kind": "drill",
  "drillVersion": "v4",
  "workspace": "de",
  "language": "de",
  "level": "A1",
  "title": "Modal Verbs: A1 (Tier 4) - Pattern",
  "shortTitle": "Modal Verbs A1 Pattern",
  "subtitle": "Tier 4 - pattern switch - Practice modal verbs (können, müss",
  "estimatedMinutes": 5,
  "mechanicId": "modal_verbs",
  "mechanicLabel": "Modal Verbs",
  "loopType": "pattern_switch",
  "difficultyTier": 4,
  "variationSlots": [
    "subject",
    "verb",
    "object",
    "modifier",
    "time"
  ],
  "sessionPlan": {
    "version": 1,
    "steps": [
      {
        "id": "pattern-1",
        "title": "Pattern 1: Basic Forms",
        "promptIds": [
          "prompt-001",
          "prompt-002"
        ],
        "title_i18n": {
          "en": "Pattern 1: Basic Forms"
        }
      },
      {
        "id": "pattern-2",
        "title": "Pattern 2: Extended Forms",
        "promptIds": [
          "prompt-003",
          "prompt-004"
        ],
        "title_i18n": {
          "en": "Pattern 2: Extended Forms"
        }
      },
      {
        "id": "pattern-3",
        "title": "Pattern 3: Complex Forms",
        "promptIds": [
          "prompt-005",
          "prompt-006",
          "prompt-007",
          "prompt-008",
          "prompt-009",
          "prompt-010",
          "prompt-011",
          "prompt-012"
        ],
        "title_i18n": {
          "en": "Pattern 3: Complex Forms"
        }
      }
    ]
  },
  "prompts": [
    {
      "id": "prompt-001",
      "text": "bald sollen wir bei Freunden lernen.",
      "intent": "practice",
      "gloss_en": "I am practicing this grammar mechanic.",
      "natural_en": "bald sollen wir bei Freunden lernen.",
      "slotsChanged": [
        "subject",
        "verb",
        "time",
        "location"
      ],
      "slots": {
        "subject": [
          "Wir"
        ],
        "verb": [
          "sollen"
        ],
        "time": [
          "bald"
        ],
        "location": [
          "bei Freunden"
        ],
        "infinitive": [
          "lernen"
        ]
      },
      "audioUrl": "/v1/audio/modal_verbs_A1_tier4/prompt-001.mp3"
    },
    {
      "id": "prompt-002",
      "text": "am Wochenende sollen wir hier den kaufen.",
      "intent": "practice",
      "gloss_en": "I am practicing this grammar mechanic.",
      "natural_en": "am Wochenende sollen wir hier den kaufen.",
      "slotsChanged": [
        "subject",
        "verb",
        "object",
        "time",
        "location"
      ],
      "slots": {
        "subject": [
          "Wir"
        ],
        "verb": [
          "sollen"
        ],
        "object": [
          "den"
        ],
        "time": [
          "am Wochenende"
        ],
        "location": [
          "hier"
        ],
        "infinitive": [
          "kaufen"
        ]
      },
      "audioUrl": "/v1/audio/modal_verbs_A1_tier4/prompt-002.mp3"
    },
    {
      "id": "prompt-003",
      "text": "bald kannst du dort die gehen.",
      "intent": "practice",
      "gloss_en": "I am practicing this grammar mechanic.",
      "natural_en": "bald kannst du dort die gehen.",
      "slotsChanged": [
        "time",
        "subject",
        "verb",
        "location",
        "object"
      ],
      "slots": {
        "subject": [
          "Du"
        ],
        "verb": [
          "kannst"
        ],
        "object": [
          "die"
        ],
        "time": [
          "bald"
        ],
        "location": [
          "dort"
        ],
        "infinitive": [
          "gehen"
        ]
      },
      "audioUrl": "/v1/audio/modal_verbs_A1_tier4/prompt-003.mp3"
    },
    {
      "id": "prompt-004",
      "text": "am Wochenende willst du bei Freunden machen.",
      "intent": "practice",
      "gloss_en": "I am practicing this grammar mechanic.",
      "natural_en": "am Wochenende willst du bei Freunden machen.",
      "slotsChanged": [
        "subject",
        "verb",
        "time",
        "location"
      ],
      "slots": {
        "subject": [
          "Du"
        ],
        "verb": [
          "willst"
        ],
        "time": [
          "am Wochenende"
        ],
        "location": [
          "bei Freunden"
        ],
        "infinitive": [
          "machen"
        ]
      },
      "audioUrl": "/v1/audio/modal_verbs_A1_tier4/prompt-004.mp3"
    },
    {
      "id": "prompt-005",
      "text": "bald könnt ihr bei Freunden eine hören.",
      "intent": "practice",
      "gloss_en": "I am practicing this grammar mechanic.",
      "natural_en": "bald könnt ihr bei Freunden eine hören.",
      "slotsChanged": [
        "subject",
        "verb",
        "object",
        "time",
        "location"
      ],
      "slots": {
        "subject": [
          "Ihr"
        ],
        "verb": [
          "könnt"
        ],
        "object": [
          "eine"
        ],
        "time": [
          "bald"
        ],
        "location": [
          "bei Freunden"
        ],
        "infinitive": [
          "hören"
        ]
      },
      "audioUrl": "/v1/audio/modal_verbs_A1_tier4/prompt-005.mp3"
    },
    {
      "id": "prompt-006",
      "text": "nächste Woche müsst ihr im Büro essen.",
      "intent": "practice",
      "gloss_en": "I am practicing this grammar mechanic.",
      "natural_en": "nächste Woche müsst ihr im Büro essen.",
      "slotsChanged": [
        "time",
        "subject",
        "verb",
        "location"
      ],
      "slots": {
        "subject": [
          "Ihr"
        ],
        "verb": [
          "müsst"
        ],
        "time": [
          "nächste Woche"
        ],
        "location": [
          "im Büro"
        ],
        "infinitive": [
          "essen"
        ]
      },
      "audioUrl": "/v1/audio/modal_verbs_A1_tier4/prompt-006.mp3"
    },
    {
      "id": "prompt-007",
      "text": "am Wochenende muss er in der Stadt trinken.",
      "intent": "practice",
      "gloss_en": "I am practicing this grammar mechanic.",
      "natural_en": "am Wochenende muss er in der Stadt trinken.",
      "slotsChanged": [
        "subject",
        "verb",
        "time",
        "location"
      ],
      "slots": {
        "subject": [
          "Er"
        ],
        "verb": [
          "muss"
        ],
        "time": [
          "am Wochenende"
        ],
        "location": [
          "in der Stadt"
        ],
        "infinitive": [
          "trinken"
        ]
      },
      "audioUrl": "/v1/audio/modal_verbs_A1_tier4/prompt-007.mp3"
    },
    {
      "id": "prompt-008",
      "text": "heute will er dort den sehen.",
      "intent": "practice",
      "gloss_en": "I am practicing this grammar mechanic.",
      "natural_en": "heute will er dort den sehen.",
      "slotsChanged": [
        "subject",
        "verb",
        "object",
        "time",
        "location"
      ],
      "slots": {
        "subject": [
          "Er"
        ],
        "verb": [
          "will"
        ],
        "object": [
          "den"
        ],
        "time": [
          "heute"
        ],
        "location": [
          "dort"
        ],
        "infinitive": [
          "sehen"
        ]
      },
      "audioUrl": "/v1/audio/modal_verbs_A1_tier4/prompt-008.mp3"
    },
    {
      "id": "prompt-009",
      "text": "nächste Woche will ich hier arbeiten.",
      "intent": "practice",
      "gloss_en": "I am practicing this grammar mechanic.",
      "natural_en": "nächste Woche will ich hier arbeiten.",
      "slotsChanged": [
        "time",
        "subject",
        "verb",
        "location"
      ],
      "slots": {
        "subject": [
          "Ich"
        ],
        "verb": [
          "will"
        ],
        "time": [
          "nächste Woche"
        ],
        "location": [
          "hier"
        ],
        "infinitive": [
          "arbeiten"
        ]
      },
      "audioUrl": "/v1/audio/modal_verbs_A1_tier4/prompt-009.mp3"
    },
    {
      "id": "prompt-010",
      "text": "später muss ich in der Stadt schlafen.",
      "intent": "practice",
      "gloss_en": "I am practicing this grammar mechanic.",
      "natural_en": "später muss ich in der Stadt schlafen.",
      "slotsChanged": [
        "subject",
        "verb",
        "time",
        "location"
      ],
      "slots": {
        "subject": [
          "Ich"
        ],
        "verb": [
          "muss"
        ],
        "time": [
          "später"
        ],
        "location": [
          "in der Stadt"
        ],
        "infinitive": [
          "schlafen"
        ]
      },
      "audioUrl": "/v1/audio/modal_verbs_A1_tier4/prompt-010.mp3"
    },
    {
      "id": "prompt-011",
      "text": "bald kann Sie zu Hause eine spielen.",
      "intent": "practice",
      "gloss_en": "I am practicing this grammar mechanic.",
      "natural_en": "bald kann Sie zu Hause eine spielen.",
      "slotsChanged": [
        "subject",
        "verb",
        "object",
        "time",
        "location"
      ],
      "slots": {
        "subject": [
          "Sie"
        ],
        "verb": [
          "kann"
        ],
        "object": [
          "eine"
        ],
        "time": [
          "bald"
        ],
        "location": [
          "zu Hause"
        ],
        "infinitive": [
          "spielen"
        ]
      },
      "audioUrl": "/v1/audio/modal_verbs_A1_tier4/prompt-011.mp3"
    },
    {
      "id": "prompt-012",
      "text": "bald muss Sie hier Deutsch kommen.",
      "intent": "practice",
      "gloss_en": "I am practicing this grammar mechanic.",
      "natural_en": "bald muss Sie hier Deutsch kommen.",
      "slotsChanged": [
        "time",
        "subject",
        "verb",
        "location",
        "object"
      ],
      "slots": {
        "subject": [
          "Sie"
        ],
        "verb": [
          "muss"
        ],
        "object": [
          "Deutsch"
        ],
        "time": [
          "bald"
        ],
        "location": [
          "hier"
        ],
        "infinitive": [
          "kommen"
        ]
      },
      "audioUrl": "/v1/audio/modal_verbs_A1_tier4/prompt-012.mp3"
    }
  ],
  "analytics": {
    "version": 1,
    "mechanicId": "modal_verbs",
    "loopType": "pattern_switch",
    "targetStructures": [
      "modal_verb_infinitive",
      "modal_verb_requests",
      "modal_verb_ability"
    ],
    "variationSlots": [
      "subject",
      "verb"
    ],
    "coverage": {
      "verbs": [
        "sollen",
        "kannst",
        "willst",
        "könnt",
        "müsst",
        "muss",
        "will",
        "kann"
      ],
      "subjects": [
        "Wir",
        "Du",
        "Ihr",
        "Er",
        "Ich",
        "Sie"
      ],
      "patterns": [
        "modal_verb_infinitive",
        "modal_verb_requests",
        "modal_verb_ability"
      ]
    },
    "difficultyTier": 4,
    "recommendedReps": 4,
    "estPromptCount": 12,
    "timeboxMinutes": 5,
    "qualitySignals": {
      "tokenHitsCount": 12,
      "multiSlotRate": 1,
      "uniqueVerbCount": 8,
      "uniqueSubjectCount": 6,
      "trapPairCount": 0,
      "bannedPhraseCheckPassed": true
    }
  },
  "provenance": {
    "source": "template",
    "sourceRef": "mechanics/modal_verbs",
    "extractorVersion": "v4.0.0",
    "generatedAt": "2026-01-04T06:49:17.656Z"
  },
  "review": {
    "status": "needs_review"
  },
  "title_i18n": {
    "en": "Modal Verbs: A1 (Tier 4) - Pattern"
  },
  "shortTitle_i18n": {
    "en": "Modal Verbs A1 Pattern"
  },
  "subtitle_i18n": {
    "en": "Tier 4 - pattern switch - Practice modal verbs (können, müss"
  },
  "contentId": "de:drill:modal_verbs_a1_tier4_pattern-switch",
  "contentHash": "bd0c511d4abb534572a1ab52a4b9366b40ed043aa03672ba952f3aaf1fff0e96",
  "revisionId": "bd0c511d4abb"
}
