{
  "version": "v1",
  "kind": "drills",
  "total": 4,
  "pageSize": 2,
  "items": [
    {
      "id": "separable_verbs_a1",
      "kind": "drill",
      "title": "Separable Verbs",
      "level": "A1",
      "durationMinutes": 15,
      "entryUrl": "/v1/workspaces/de/drills/separable_verbs_a1/drill.json",
      "tags": [
        "grammar",
        "verbs",
        "separable-verbs",
        "conjugation"
      ]
    },
    {
      "id": "verb_endings_a1",
      "kind": "drill",
      "title": "Verb Endings - Present Tense",
      "level": "A1",
      "durationMinutes": 10,
      "entryUrl": "/v1/workspaces/de/drills/verb_endings_a1/drill.json",
      "tags": [
        "grammar",
        "verbs",
        "conjugation",
        "present-tense"
      ]
    }
  ],
  "nextPage": null
}
