{
  "schemaVersion": 1,
  "id": "question_formation_a1_tier2_fast-recall",
  "kind": "drill",
  "drillVersion": "v4",
  "workspace": "de",
  "language": "de",
  "level": "A1",
  "title": "Question Formation: A1 (Tier 2)",
  "shortTitle": "Question Formation A1",
  "subtitle": "Tier 2 - fast recall - Form questions using question words a",
  "estimatedMinutes": 4,
  "mechanicId": "question_formation",
  "mechanicLabel": "Question Formation",
  "loopType": "fast_recall",
  "difficultyTier": 2,
  "variationSlots": [
    "subject",
    "verb",
    "object"
  ],
  "sessionPlan": {
    "version": 1,
    "steps": [
      {
        "id": "step-1",
        "title": "Step 1",
        "promptIds": [
          "prompt-001",
          "prompt-002",
          "prompt-003"
        ],
        "title_i18n": {
          "en": "Step 1"
        }
      },
      {
        "id": "step-2",
        "title": "Step 2",
        "promptIds": [
          "prompt-004",
          "prompt-005",
          "prompt-006"
        ],
        "title_i18n": {
          "en": "Step 2"
        }
      },
      {
        "id": "step-3",
        "title": "Step 3",
        "promptIds": [
          "prompt-007",
          "prompt-008"
        ],
        "title_i18n": {
          "en": "Step 3"
        }
      }
    ]
  },
  "prompts": [
    {
      "id": "prompt-001",
      "text": "Sie kommt die.",
      "intent": "practice",
      "gloss_en": "I am practicing this grammar mechanic.",
      "natural_en": "Sie kommt die.",
      "slotsChanged": [
        "subject",
        "verb",
        "object"
      ],
      "slots": {
        "subject": [
          "Sie"
        ],
        "verb": [
          "kommt"
        ],
        "object": [
          "die"
        ]
      },
      "audioUrl": "/v1/audio/question_formation_A1_tier2/prompt-001.mp3"
    },
    {
      "id": "prompt-002",
      "text": "Sie wohnt den.",
      "intent": "practice",
      "gloss_en": "I am practicing this grammar mechanic.",
      "natural_en": "Sie wohnt den.",
      "slotsChanged": [
        "subject",
        "verb",
        "object"
      ],
      "slots": {
        "subject": [
          "Sie"
        ],
        "verb": [
          "wohnt"
        ],
        "object": [
          "den"
        ]
      },
      "audioUrl": "/v1/audio/question_formation_A1_tier2/prompt-002.mp3"
    },
    {
      "id": "prompt-003",
      "text": "ihr arbeitt das.",
      "intent": "practice",
      "gloss_en": "I am practicing this grammar mechanic.",
      "natural_en": "ihr arbeitt das.",
      "slotsChanged": [
        "subject",
        "verb",
        "object"
      ],
      "slots": {
        "subject": [
          "ihr"
        ],
        "verb": [
          "arbeitt"
        ],
        "object": [
          "das"
        ]
      },
      "audioUrl": "/v1/audio/question_formation_A1_tier2/prompt-003.mp3"
    },
    {
      "id": "prompt-004",
      "text": "er lernt einen.",
      "intent": "practice",
      "gloss_en": "I am practicing this grammar mechanic.",
      "natural_en": "er lernt einen.",
      "slotsChanged": [
        "subject",
        "verb",
        "object"
      ],
      "slots": {
        "subject": [
          "er"
        ],
        "verb": [
          "lernt"
        ],
        "object": [
          "einen"
        ]
      },
      "audioUrl": "/v1/audio/question_formation_A1_tier2/prompt-004.mp3"
    },
    {
      "id": "prompt-005",
      "text": "Sie macht das.",
      "intent": "practice",
      "gloss_en": "I am practicing this grammar mechanic.",
      "natural_en": "Sie macht das.",
      "slotsChanged": [
        "subject",
        "verb",
        "object"
      ],
      "slots": {
        "subject": [
          "Sie"
        ],
        "verb": [
          "macht"
        ],
        "object": [
          "das"
        ]
      },
      "audioUrl": "/v1/audio/question_formation_A1_tier2/prompt-005.mp3"
    },
    {
      "id": "prompt-006",
      "text": "Sie lernt einen.",
      "intent": "practice",
      "gloss_en": "I am practicing this grammar mechanic.",
      "natural_en": "Sie lernt einen.",
      "slotsChanged": [
        "subject",
        "verb",
        "object"
      ],
      "slots": {
        "subject": [
          "Sie"
        ],
        "verb": [
          "lernt"
        ],
        "object": [
          "einen"
        ]
      },
      "audioUrl": "/v1/audio/question_formation_A1_tier2/prompt-006.mp3"
    },
    {
      "id": "prompt-007",
      "text": "er macht die.",
      "intent": "practice",
      "gloss_en": "I am practicing this grammar mechanic.",
      "natural_en": "er macht die.",
      "slotsChanged": [
        "subject",
        "verb",
        "object"
      ],
      "slots": {
        "subject": [
          "er"
        ],
        "verb": [
          "macht"
        ],
        "object": [
          "die"
        ]
      },
      "audioUrl": "/v1/audio/question_formation_A1_tier2/prompt-007.mp3"
    },
    {
      "id": "prompt-008",
      "text": "du arbeitst eine.",
      "intent": "practice",
      "gloss_en": "I am practicing this grammar mechanic.",
      "natural_en": "du arbeitst eine.",
      "slotsChanged": [
        "subject",
        "verb",
        "object"
      ],
      "slots": {
        "subject": [
          "du"
        ],
        "verb": [
          "arbeitst"
        ],
        "object": [
          "eine"
        ]
      },
      "audioUrl": "/v1/audio/question_formation_A1_tier2/prompt-008.mp3"
    }
  ],
  "analytics": {
    "version": 1,
    "mechanicId": "question_formation",
    "loopType": "fast_recall",
    "targetStructures": [
      "question_word_order",
      "verb_inversion",
      "yes_no_questions"
    ],
    "variationSlots": [
      "subject",
      "verb"
    ],
    "coverage": {
      "verbs": [
        "kommt",
        "wohnt",
        "arbeitt",
        "lernt",
        "macht",
        "arbeitst"
      ],
      "subjects": [
        "Sie",
        "ihr",
        "er",
        "du"
      ],
      "patterns": [
        "question_word_order",
        "verb_inversion",
        "yes_no_questions"
      ]
    },
    "difficultyTier": 2,
    "recommendedReps": 3,
    "estPromptCount": 8,
    "timeboxMinutes": 4,
    "qualitySignals": {
      "tokenHitsCount": 1,
      "multiSlotRate": 1,
      "uniqueVerbCount": 6,
      "uniqueSubjectCount": 4,
      "trapPairCount": 0,
      "bannedPhraseCheckPassed": true
    }
  },
  "provenance": {
    "source": "template",
    "sourceRef": "mechanics/question_formation",
    "extractorVersion": "v4.0.0",
    "generatedAt": "2026-01-03T00:18:10.648Z"
  },
  "review": {
    "status": "needs_review"
  },
  "contentId": "de:drill:question_formation_a1_tier2_fast-recall",
  "contentHash": "df41b0c8db8fc933839786dd7329d6f9697c727ac3a2a75c2e2786516d1ec361",
  "revisionId": "df41b0c8db8f"
}
