{
  "schemaVersion": 1,
  "id": "negation_a1_tier3_pattern-switch",
  "kind": "drill",
  "drillVersion": "v4",
  "workspace": "de",
  "language": "de",
  "level": "A1",
  "title": "Negation: A1 (Tier 3) - Pattern",
  "shortTitle": "Negation A1 Pattern",
  "subtitle": "Tier 3 - pattern switch - Master negation placement (nicht, ",
  "estimatedMinutes": 5,
  "mechanicId": "negation",
  "mechanicLabel": "Negation",
  "loopType": "pattern_switch",
  "difficultyTier": 3,
  "variationSlots": [
    "subject",
    "verb",
    "object",
    "modifier",
    "time"
  ],
  "sessionPlan": {
    "version": 1,
    "steps": [
      {
        "id": "pattern-1",
        "title": "Pattern 1: Basic Forms",
        "promptIds": [
          "prompt-001",
          "prompt-002"
        ],
        "title_i18n": {
          "en": "Pattern 1: Basic Forms"
        }
      },
      {
        "id": "pattern-2",
        "title": "Pattern 2: Extended Forms",
        "promptIds": [
          "prompt-003",
          "prompt-004"
        ],
        "title_i18n": {
          "en": "Pattern 2: Extended Forms"
        }
      },
      {
        "id": "pattern-3",
        "title": "Pattern 3: Complex Forms",
        "promptIds": [
          "prompt-005",
          "prompt-006",
          "prompt-007",
          "prompt-008",
          "prompt-009",
          "prompt-010"
        ],
        "title_i18n": {
          "en": "Pattern 3: Complex Forms"
        }
      }
    ]
  },
  "prompts": [
    {
      "id": "prompt-001",
      "text": "jetzt habest du im Kino.",
      "intent": "practice",
      "gloss_en": "I am practicing this grammar mechanic.",
      "natural_en": "jetzt habest du im Kino.",
      "slotsChanged": [
        "subject",
        "verb",
        "time",
        "location"
      ],
      "slots": {
        "subject": [
          "Du"
        ],
        "verb": [
          "habest"
        ],
        "time": [
          "jetzt"
        ],
        "location": [
          "im Kino"
        ]
      },
      "audioUrl": "/v1/audio/negation_A1_tier3/prompt-001.mp3"
    },
    {
      "id": "prompt-002",
      "text": "heute habe ich im Büro die Musik.",
      "intent": "practice",
      "gloss_en": "I am practicing this grammar mechanic.",
      "natural_en": "heute habe ich im Büro die Musik.",
      "slotsChanged": [
        "subject",
        "verb",
        "object",
        "time",
        "location"
      ],
      "slots": {
        "subject": [
          "Ich"
        ],
        "verb": [
          "habe"
        ],
        "object": [
          "die Musik"
        ],
        "time": [
          "heute"
        ],
        "location": [
          "im Büro"
        ]
      },
      "audioUrl": "/v1/audio/negation_A1_tier3/prompt-002.mp3"
    },
    {
      "id": "prompt-003",
      "text": "am Abend gehe er hier Kaffee.",
      "intent": "practice",
      "gloss_en": "I am practicing this grammar mechanic.",
      "natural_en": "am Abend gehe er hier Kaffee.",
      "slotsChanged": [
        "time",
        "subject",
        "verb",
        "location",
        "object"
      ],
      "slots": {
        "subject": [
          "Er"
        ],
        "verb": [
          "gehe"
        ],
        "object": [
          "Kaffee"
        ],
        "time": [
          "am Abend"
        ],
        "location": [
          "hier"
        ]
      },
      "audioUrl": "/v1/audio/negation_A1_tier3/prompt-003.mp3"
    },
    {
      "id": "prompt-004",
      "text": "später bin wir hier das Buch.",
      "intent": "practice",
      "gloss_en": "I am practicing this grammar mechanic.",
      "natural_en": "später bin wir hier das Buch.",
      "slotsChanged": [
        "subject",
        "verb",
        "time",
        "location",
        "object"
      ],
      "slots": {
        "subject": [
          "Wir"
        ],
        "verb": [
          "bin"
        ],
        "object": [
          "das Buch"
        ],
        "time": [
          "später"
        ],
        "location": [
          "hier"
        ]
      },
      "audioUrl": "/v1/audio/negation_A1_tier3/prompt-004.mp3"
    },
    {
      "id": "prompt-005",
      "text": "jetzt habe Sie zu Hause den Film.",
      "intent": "practice",
      "gloss_en": "I am practicing this grammar mechanic.",
      "natural_en": "jetzt habe Sie zu Hause den Film.",
      "slotsChanged": [
        "subject",
        "verb",
        "object",
        "time",
        "location"
      ],
      "slots": {
        "subject": [
          "Sie"
        ],
        "verb": [
          "habe"
        ],
        "object": [
          "den Film"
        ],
        "time": [
          "jetzt"
        ],
        "location": [
          "zu Hause"
        ]
      },
      "audioUrl": "/v1/audio/negation_A1_tier3/prompt-005.mp3"
    },
    {
      "id": "prompt-006",
      "text": "später komme ihr im Kino.",
      "intent": "practice",
      "gloss_en": "I am practicing this grammar mechanic.",
      "natural_en": "später komme ihr im Kino.",
      "slotsChanged": [
        "time",
        "subject",
        "verb",
        "location"
      ],
      "slots": {
        "subject": [
          "Ihr"
        ],
        "verb": [
          "komme"
        ],
        "time": [
          "später"
        ],
        "location": [
          "im Kino"
        ]
      },
      "audioUrl": "/v1/audio/negation_A1_tier3/prompt-006.mp3"
    },
    {
      "id": "prompt-007",
      "text": "heute kommest du hier die Zeitung.",
      "intent": "practice",
      "gloss_en": "I am practicing this grammar mechanic.",
      "natural_en": "heute kommest du hier die Zeitung.",
      "slotsChanged": [
        "subject",
        "verb",
        "time",
        "location",
        "object"
      ],
      "slots": {
        "subject": [
          "Du"
        ],
        "verb": [
          "kommest"
        ],
        "object": [
          "die Zeitung"
        ],
        "time": [
          "heute"
        ],
        "location": [
          "hier"
        ]
      },
      "audioUrl": "/v1/audio/negation_A1_tier3/prompt-007.mp3"
    },
    {
      "id": "prompt-008",
      "text": "jetzt trinkee ich hier Tee.",
      "intent": "practice",
      "gloss_en": "I am practicing this grammar mechanic.",
      "natural_en": "jetzt trinkee ich hier Tee.",
      "slotsChanged": [
        "subject",
        "verb",
        "object",
        "time",
        "location"
      ],
      "slots": {
        "subject": [
          "Ich"
        ],
        "verb": [
          "trinkee"
        ],
        "object": [
          "Tee"
        ],
        "time": [
          "jetzt"
        ],
        "location": [
          "hier"
        ]
      },
      "audioUrl": "/v1/audio/negation_A1_tier3/prompt-008.mp3"
    },
    {
      "id": "prompt-009",
      "text": "am Abend gehet er hier.",
      "intent": "practice",
      "gloss_en": "I am practicing this grammar mechanic.",
      "natural_en": "am Abend gehet er hier.",
      "slotsChanged": [
        "time",
        "subject",
        "verb",
        "location"
      ],
      "slots": {
        "subject": [
          "Er"
        ],
        "verb": [
          "gehet"
        ],
        "time": [
          "am Abend"
        ],
        "location": [
          "hier"
        ]
      },
      "audioUrl": "/v1/audio/negation_A1_tier3/prompt-009.mp3"
    },
    {
      "id": "prompt-010",
      "text": "am Abend habe wir im Kino.",
      "intent": "practice",
      "gloss_en": "I am practicing this grammar mechanic.",
      "natural_en": "am Abend habe wir im Kino.",
      "slotsChanged": [
        "subject",
        "verb",
        "time",
        "location"
      ],
      "slots": {
        "subject": [
          "Wir"
        ],
        "verb": [
          "habe"
        ],
        "time": [
          "am Abend"
        ],
        "location": [
          "im Kino"
        ]
      },
      "audioUrl": "/v1/audio/negation_A1_tier3/prompt-010.mp3"
    }
  ],
  "analytics": {
    "version": 1,
    "mechanicId": "negation",
    "loopType": "pattern_switch",
    "targetStructures": [
      "nicht_placement",
      "kein_keine_keinen",
      "affirmative_to_negative"
    ],
    "variationSlots": [
      "subject",
      "verb"
    ],
    "coverage": {
      "verbs": [
        "habest",
        "habe",
        "gehe",
        "bin",
        "komme",
        "kommest",
        "trinkee",
        "gehet"
      ],
      "subjects": [
        "Du",
        "Ich",
        "Er",
        "Wir",
        "Sie",
        "Ihr"
      ],
      "patterns": [
        "nicht_placement",
        "kein_keine_keinen",
        "affirmative_to_negative"
      ]
    },
    "difficultyTier": 3,
    "recommendedReps": 4,
    "estPromptCount": 10,
    "timeboxMinutes": 5,
    "qualitySignals": {
      "tokenHitsCount": 9,
      "multiSlotRate": 1,
      "uniqueVerbCount": 8,
      "uniqueSubjectCount": 6,
      "trapPairCount": 0,
      "bannedPhraseCheckPassed": true
    }
  },
  "provenance": {
    "source": "template",
    "sourceRef": "mechanics/negation",
    "extractorVersion": "v4.0.0",
    "generatedAt": "2026-01-03T09:52:17.355Z"
  },
  "review": {
    "status": "needs_review"
  },
  "title_i18n": {
    "en": "Negation: A1 (Tier 3) - Pattern"
  },
  "shortTitle_i18n": {
    "en": "Negation A1 Pattern"
  },
  "subtitle_i18n": {
    "en": "Tier 3 - pattern switch - Master negation placement (nicht, "
  },
  "contentId": "de:drill:negation_a1_tier3_pattern-switch",
  "contentHash": "5485d435e71b477ecb913ba46a84c467b08f6c1e50cc1d1f29002f8356777a00",
  "revisionId": "5485d435e71b"
}
