{
  "schemaVersion": 1,
  "id": "doctor_pack_6_a1",
  "kind": "pack",
  "packVersion": "1.0.0",
  "title": "Doctor A1 — 6: Getting Prescription",
  "level": "A1",
  "estimatedMinutes": 15,
  "description": "Practice doctor scenarios at A1 level.",
  "scenario": "doctor",
  "register": "neutral",
  "primaryStructure": "modal_verbs_requests",
  "variationSlots": [
    "subject",
    "verb",
    "object",
    "modifier",
    "time"
  ],
  "outline": [
    "Making an Appointment",
    "Describing Symptoms",
    "Getting Prescription"
  ],
  "prompts": [
    {
      "id": "prompt-001",
      "text": "Wir haben die Behandlung um 15:00",
      "intent": "inform",
      "gloss_en": "I am providing information.",
      "natural_en": "Here's the information.",
      "audioUrl": "/v1/audio/doctor_pack_6_a1/prompt-001.mp3",
      "slotsChanged": [
        "subject",
        "verb",
        "modifier"
      ],
      "slots": {
        "subject": [
          "Wir"
        ],
        "verb": [
          "haben"
        ],
        "object": [
          "die Behandlung"
        ],
        "modifier": [
          "um 15:00"
        ]
      },
      "gloss_en_i18n": {
        "en": "I am providing information.",
        "es": "Estoy proporcionando información.",
        "fr": "Je fournis des informations.",
        "it": "Sto fornendo informazioni.",
        "pt": "Estou a fornecer informações.",
        "ru": "Я предоставляю информацию.",
        "ja": "私は情報を提供している。",
        "ko": "정보를 제공하고 있습니다.",
        "zh-CN": "我在提供信息。",
        "zh-TW": "我在提供信息。",
        "ar": "أنا أقدم المعلومات",
        "tr": "Ben bilgi veriyorum.",
        "pl": "Przekazuję informacje.",
        "nl": "Ik geef informatie.",
        "sv": "Jag tillhandahåller information.",
        "no": "Jeg gir informasjon.",
        "da": "Jeg giver information.",
        "fi": "Annan tietoja.",
        "el": "Παρέχω πληροφορίες.",
        "cs": "Poskytuji informace."
      }
    },
    {
      "id": "prompt-002",
      "text": "Die Ärztin hat einen Termin nächste Woche um 18:30",
      "intent": "schedule",
      "gloss_en": "I need to schedule something.",
      "natural_en": "I need to schedule that.",
      "audioUrl": "/v1/audio/doctor_pack_6_a1/prompt-002.mp3",
      "slotsChanged": [
        "object",
        "time"
      ],
      "slots": {
        "subject": [
          "Die Ärztin"
        ],
        "verb": [
          "hat"
        ],
        "object": [
          "einen Termin"
        ],
        "modifier": [
          "nächste Woche"
        ]
      },
      "gloss_en_i18n": {
        "en": "I need to schedule something.",
        "es": "Necesito programar algo.",
        "fr": "Je dois programmer quelque chose.",
        "it": "Devo programmare qualcosa.",
        "pt": "Preciso de marcar uma coisa.",
        "ru": "Мне нужно кое-что запланировать.",
        "ja": "何か予定を入れないと。",
        "ko": "일정을 잡아야 합니다.",
        "zh-CN": "我需要安排一些事情。",
        "zh-TW": "我需要安排一些事情。",
        "ar": "أحتاج إلى جدولة شيء ما.",
        "tr": "Bir şeyler ayarlamam lazım.",
        "pl": "Muszę coś zaplanować.",
        "nl": "Ik moet iets plannen.",
        "sv": "Jag måste planera in något.",
        "no": "Jeg må planlegge noe.",
        "da": "Jeg er nødt til at planlægge noget.",
        "fi": "Minun on varattava aikaa.",
        "el": "Πρέπει να προγραμματίσω κάτι.",
        "cs": "Musím si něco naplánovat."
      }
    },
    {
      "id": "prompt-003",
      "text": "Sie brauchen die Symptome",
      "intent": "inform",
      "gloss_en": "I am providing information.",
      "natural_en": "Here's the information.",
      "audioUrl": "/v1/audio/doctor_pack_6_a1/prompt-003.mp3",
      "slotsChanged": [
        "subject",
        "verb",
        "object"
      ],
      "slots": {
        "subject": [
          "Sie"
        ],
        "verb": [
          "brauchen"
        ],
        "object": [
          "die Symptome"
        ]
      },
      "gloss_en_i18n": {
        "en": "I am providing information.",
        "es": "Estoy proporcionando información.",
        "fr": "Je fournis des informations.",
        "it": "Sto fornendo informazioni.",
        "pt": "Estou a fornecer informações.",
        "ru": "Я предоставляю информацию.",
        "ja": "私は情報を提供している。",
        "ko": "정보를 제공하고 있습니다.",
        "zh-CN": "我在提供信息。",
        "zh-TW": "我在提供信息。",
        "ar": "أنا أقدم المعلومات",
        "tr": "Ben bilgi veriyorum.",
        "pl": "Przekazuję informacje.",
        "nl": "Ik geef informatie.",
        "sv": "Jag tillhandahåller information.",
        "no": "Jeg gir informasjon.",
        "da": "Jeg giver information.",
        "fi": "Annan tietoja.",
        "el": "Παρέχω πληροφορίες.",
        "cs": "Poskytuji informace."
      }
    },
    {
      "id": "prompt-004",
      "text": "Der Arzt hat einen Termin",
      "intent": "schedule",
      "gloss_en": "I need to schedule something.",
      "natural_en": "I need to schedule that.",
      "audioUrl": "/v1/audio/doctor_pack_6_a1/prompt-004.mp3",
      "slotsChanged": [
        "subject",
        "verb",
        "object"
      ],
      "slots": {
        "subject": [
          "Der Arzt"
        ],
        "verb": [
          "hat"
        ],
        "object": [
          "einen Termin"
        ]
      },
      "gloss_en_i18n": {
        "en": "I need to schedule something.",
        "es": "Necesito programar algo.",
        "fr": "Je dois programmer quelque chose.",
        "it": "Devo programmare qualcosa.",
        "pt": "Preciso de marcar uma coisa.",
        "ru": "Мне нужно кое-что запланировать.",
        "ja": "何か予定を入れないと。",
        "ko": "일정을 잡아야 합니다.",
        "zh-CN": "我需要安排一些事情。",
        "zh-TW": "我需要安排一些事情。",
        "ar": "أحتاج إلى جدولة شيء ما.",
        "tr": "Bir şeyler ayarlamam lazım.",
        "pl": "Muszę coś zaplanować.",
        "nl": "Ik moet iets plannen.",
        "sv": "Jag måste planera in något.",
        "no": "Jeg må planlegge noe.",
        "da": "Jeg er nødt til at planlægge noget.",
        "fi": "Minun on varattava aikaa.",
        "el": "Πρέπει να προγραμματίσω κάτι.",
        "cs": "Musím si něco naplánovat."
      }
    },
    {
      "id": "prompt-005",
      "text": "Der Arzt muss die Behandlung",
      "intent": "inform",
      "gloss_en": "I am providing information.",
      "natural_en": "Here's the information.",
      "audioUrl": "/v1/audio/doctor_pack_6_a1/prompt-005.mp3",
      "slotsChanged": [
        "verb",
        "object"
      ],
      "slots": {
        "subject": [
          "Der Arzt"
        ],
        "verb": [
          "muss"
        ],
        "object": [
          "die Behandlung"
        ]
      },
      "gloss_en_i18n": {
        "en": "I am providing information.",
        "es": "Estoy proporcionando información.",
        "fr": "Je fournis des informations.",
        "it": "Sto fornendo informazioni.",
        "pt": "Estou a fornecer informações.",
        "ru": "Я предоставляю информацию.",
        "ja": "私は情報を提供している。",
        "ko": "정보를 제공하고 있습니다.",
        "zh-CN": "我在提供信息。",
        "zh-TW": "我在提供信息。",
        "ar": "أنا أقدم المعلومات",
        "tr": "Ben bilgi veriyorum.",
        "pl": "Przekazuję informacje.",
        "nl": "Ik geef informatie.",
        "sv": "Jag tillhandahåller information.",
        "no": "Jeg gir informasjon.",
        "da": "Jeg giver information.",
        "fi": "Annan tietoja.",
        "el": "Παρέχω πληροφορίες.",
        "cs": "Poskytuji informace."
      }
    },
    {
      "id": "prompt-006",
      "text": "Der Arzt vereinbart die Medikamente",
      "intent": "inform",
      "gloss_en": "I am providing information.",
      "natural_en": "Here's the information.",
      "audioUrl": "/v1/audio/doctor_pack_6_a1/prompt-006.mp3",
      "slotsChanged": [
        "verb",
        "object"
      ],
      "slots": {
        "subject": [
          "Der Arzt"
        ],
        "verb": [
          "vereinbart"
        ],
        "object": [
          "die Medikamente"
        ]
      },
      "gloss_en_i18n": {
        "en": "I am providing information.",
        "es": "Estoy proporcionando información.",
        "fr": "Je fournis des informations.",
        "it": "Sto fornendo informazioni.",
        "pt": "Estou a fornecer informações.",
        "ru": "Я предоставляю информацию.",
        "ja": "私は情報を提供している。",
        "ko": "정보를 제공하고 있습니다.",
        "zh-CN": "我在提供信息。",
        "zh-TW": "我在提供信息。",
        "ar": "أنا أقدم المعلومات",
        "tr": "Ben bilgi veriyorum.",
        "pl": "Przekazuję informacje.",
        "nl": "Ik geef informatie.",
        "sv": "Jag tillhandahåller information.",
        "no": "Jeg gir informasjon.",
        "da": "Jeg giver information.",
        "fi": "Annan tietoja.",
        "el": "Παρέχω πληροφορίες.",
        "cs": "Poskytuji informace."
      }
    },
    {
      "id": "prompt-007",
      "text": "Sie fühlen die Medikamente heute",
      "intent": "inform",
      "gloss_en": "I am providing information.",
      "natural_en": "Here's the information.",
      "audioUrl": "/v1/audio/doctor_pack_6_a1/prompt-007.mp3",
      "slotsChanged": [
        "subject",
        "verb"
      ],
      "slots": {
        "subject": [
          "Sie"
        ],
        "verb": [
          "fühlen"
        ],
        "object": [
          "die Medikamente"
        ],
        "modifier": [
          "heute"
        ]
      },
      "gloss_en_i18n": {
        "en": "I am providing information.",
        "es": "Estoy proporcionando información.",
        "fr": "Je fournis des informations.",
        "it": "Sto fornendo informazioni.",
        "pt": "Estou a fornecer informações.",
        "ru": "Я предоставляю информацию.",
        "ja": "私は情報を提供している。",
        "ko": "정보를 제공하고 있습니다.",
        "zh-CN": "我在提供信息。",
        "zh-TW": "我在提供信息。",
        "ar": "أنا أقدم المعلومات",
        "tr": "Ben bilgi veriyorum.",
        "pl": "Przekazuję informacje.",
        "nl": "Ik geef informatie.",
        "sv": "Jag tillhandahåller information.",
        "no": "Jeg gir informasjon.",
        "da": "Jeg giver information.",
        "fi": "Annan tietoja.",
        "el": "Παρέχω πληροφορίες.",
        "cs": "Poskytuji informace."
      }
    }
  ],
  "sessionPlan": {
    "version": 1,
    "steps": [
      {
        "id": "appointment",
        "title": "Making an Appointment",
        "promptIds": [
          "prompt-001",
          "prompt-002"
        ],
        "title_i18n": {
          "en": "Making an Appointment"
        }
      },
      {
        "id": "symptoms",
        "title": "Describing Symptoms",
        "promptIds": [
          "prompt-003",
          "prompt-004",
          "prompt-005"
        ],
        "title_i18n": {
          "en": "Describing Symptoms"
        }
      },
      {
        "id": "prescription",
        "title": "Getting Prescription",
        "promptIds": [
          "prompt-006",
          "prompt-007"
        ],
        "title_i18n": {
          "en": "Getting Prescription"
        }
      }
    ]
  },
  "tags": [
    "doctor"
  ],
  "analytics": {
    "goal": "Practice doctor appointments and health conversations at A1 level",
    "constraints": [
      "neutral register maintained",
      "doctor scenario context",
      "modal_verbs_requests structure focus",
      "verb position: second"
    ],
    "levers": [
      "subject variation",
      "verb substitution",
      "object variation",
      "modifier changes",
      "time expressions"
    ],
    "successCriteria": [
      "Uses appointment scheduling phrases",
      "Includes symptom/health vocabulary",
      "Maintains appropriate formality"
    ],
    "commonMistakes": [
      "Missing appointment vocabulary",
      "Incorrect symptom description forms",
      "Mixing formal/informal address"
    ],
    "drillType": "substitution",
    "version": 1,
    "qualityGateVersion": "qg-2025-01-01",
    "promptCount": 7,
    "multiSlotRate": 1,
    "scenarioTokenHitAvg": 0.14285714285714285,
    "scenarioTokenQualifiedRate": 0,
    "uniqueTokenRate": 0.5897435897435898,
    "bannedPhraseViolations": 0,
    "passesQualityGates": false,
    "focus": "modal_verbs",
    "cognitiveLoad": "high",
    "responseSpeedTargetMs": 1800,
    "fluencyOutcome": "health_appointments",
    "whyThisWorks": [
      "Uses appointment scheduling phrases",
      "Includes symptom/health vocabulary",
      "Maintains appropriate formality"
    ],
    "primaryStructure": "modal_verbs_requests",
    "variationSlots": [
      "subject",
      "verb",
      "object",
      "modifier",
      "time"
    ],
    "slotSwitchDensity": 1,
    "promptDiversityScore": 0.44933851377797995,
    "scenarioCoverageScore": 0.5714285714285714,
    "estimatedCognitiveLoad": "high",
    "intendedOutcome": "A1 doctor readiness",
    "targetLatencyMs": 1800,
    "successDefinition": "Practice doctor appointments and health conversations at A1 level",
    "keyFailureModes": [
      "Missing appointment vocabulary",
      "Incorrect symptom description forms",
      "Mixing formal/informal address"
    ],
    "exitConditions": {
      "targetMinutes": 15,
      "completeWhen": "sessionPlan_completed_once"
    }
  },
  "provenance": {
    "source": "template",
    "sourceRef": "doctor",
    "extractorVersion": "1.0.0",
    "generatedAt": "2026-01-01T00:56:03.895Z"
  },
  "review": {
    "status": "approved",
    "reviewer": "system",
    "reviewedAt": "2026-01-03T07:30:00.000Z"
  },
  "contentId": "de:pack:doctor_pack_6_a1",
  "contentHash": "e7ceaed78804b1fc55f9803a4d137b7d19cadef573e68987906a1cdfe2c24d5a",
  "revisionId": "e7ceaed78804",
  "title_i18n": {
    "en": "Doctor A1 — 6: Getting Prescription",
    "es": "Doctor A1 - 6: Conseguir la receta",
    "fr": "Docteur A1 - 6 : Obtenir une ordonnance",
    "it": "Medico A1 - 6: Ottenere la prescrizione",
    "pt": "Doctor A1 - 6: Receber uma receita",
    "ru": "Доктор A1 - 6: Получение рецепта",
    "ja": "ドクターA1 - 6: 処方箋をもらう",
    "ko": "닥터 A1 - 6: 처방전 받기",
    "zh-CN": "医生 A1 - 6：获取处方",
    "zh-TW": "医生 A1 - 6：获取处方",
    "ar": "الطبيب أ 1 - 6: الحصول على وصفة طبية",
    "tr": "Doktor A1 - 6: Reçete Alma",
    "pl": "Doctor A1 - 6: Otrzymanie recepty",
    "nl": "Dokter A1 - 6: een recept krijgen",
    "sv": "Doktor A1 - 6: Att få recept",
    "no": "Lege A1 - 6: Få resept",
    "da": "Læge A1 - 6: At få recept",
    "fi": "Lääkäri A1 - 6: Reseptin saaminen",
    "el": "Γιατρός A1 - 6: Συνταγογράφηση",
    "cs": "Lékař A1 - 6: Získání lékařského předpisu"
  },
  "description_i18n": {
    "en": "Practice doctor scenarios at A1 level.",
    "es": "Practicar escenarios de médicos a nivel A1.",
    "fr": "Pratiquer des scénarios de médecins au niveau A1.",
    "it": "Esercitarsi in scenari medici di livello A1.",
    "pt": "Praticar cenários médicos ao nível A1.",
    "ru": "Практикуйте сценарии для врачей на уровне A1.",
    "ja": "A1レベルの医師シナリオを練習する。",
    "ko": "A1 수준의 의사 시나리오를 연습하세요.",
    "zh-CN": "以 A1 水平练习医生情景。",
    "zh-TW": "以 A1 水平练习医生情景。",
    "ar": "تدرب على سيناريوهات الطبيب في المستوى A1.",
    "tr": "A1 seviyesinde doktor senaryolarını uygulayın.",
    "pl": "Przećwicz scenariusze dla lekarzy na poziomie A1.",
    "nl": "Oefen doktersscenario's op A1-niveau.",
    "sv": "Öva på läkarscenarier på A1-nivå.",
    "no": "Øv deg på legescenarioer på A1-nivå.",
    "da": "Øv dig på lægescenarier på A1-niveau.",
    "fi": "Harjoittele lääkärin skenaarioita A1-tasolla.",
    "el": "Πρακτική εξάσκηση σε σενάρια γιατρών σε επίπεδο Α1.",
    "cs": "Procvičování scénářů pro lékaře na úrovni A1."
  }
}
