{
  "schemaVersion": 1,
  "id": "modal_verbs_b1_tier4_pattern-switch",
  "kind": "drill",
  "drillVersion": "v4",
  "workspace": "de",
  "language": "de",
  "level": "B1",
  "title": "Modal Verbs: B1 (Tier 4) - Pattern",
  "shortTitle": "Modal Verbs B1 Pattern",
  "subtitle": "Tier 4 - pattern switch - Practice modal verbs (können, müss",
  "estimatedMinutes": 5,
  "mechanicId": "modal_verbs",
  "mechanicLabel": "Modal Verbs",
  "loopType": "pattern_switch",
  "difficultyTier": 4,
  "variationSlots": [
    "subject",
    "verb",
    "object",
    "modifier",
    "time"
  ],
  "sessionPlan": {
    "version": 1,
    "steps": [
      {
        "id": "pattern-1",
        "title": "Pattern 1: Basic Forms",
        "promptIds": [
          "prompt-001",
          "prompt-002"
        ],
        "title_i18n": {
          "en": "Pattern 1: Basic Forms"
        }
      },
      {
        "id": "pattern-2",
        "title": "Pattern 2: Extended Forms",
        "promptIds": [
          "prompt-003",
          "prompt-004"
        ],
        "title_i18n": {
          "en": "Pattern 2: Extended Forms"
        }
      },
      {
        "id": "pattern-3",
        "title": "Pattern 3: Complex Forms",
        "promptIds": [
          "prompt-005",
          "prompt-006",
          "prompt-007",
          "prompt-008",
          "prompt-009",
          "prompt-010",
          "prompt-011",
          "prompt-012"
        ],
        "title_i18n": {
          "en": "Pattern 3: Complex Forms"
        }
      }
    ]
  },
  "prompts": [
    {
      "id": "prompt-001",
      "text": "nächste Woche können wir bei Freunden arbeiten.",
      "intent": "practice",
      "gloss_en": "I am practicing this grammar mechanic.",
      "natural_en": "nächste Woche können wir bei Freunden arbeiten.",
      "slotsChanged": [
        "subject",
        "verb",
        "time",
        "location"
      ],
      "slots": {
        "subject": [
          "Wir"
        ],
        "verb": [
          "können"
        ],
        "time": [
          "nächste Woche"
        ],
        "location": [
          "bei Freunden"
        ],
        "infinitive": [
          "arbeiten"
        ]
      },
      "audioUrl": "/v1/audio/modal_verbs_B1_tier4/prompt-001.mp3"
    },
    {
      "id": "prompt-002",
      "text": "morgen müssen wir dort es machen.",
      "intent": "practice",
      "gloss_en": "I am practicing this grammar mechanic.",
      "natural_en": "morgen müssen wir dort es machen.",
      "slotsChanged": [
        "subject",
        "verb",
        "object",
        "time",
        "location"
      ],
      "slots": {
        "subject": [
          "Wir"
        ],
        "verb": [
          "müssen"
        ],
        "object": [
          "es"
        ],
        "time": [
          "morgen"
        ],
        "location": [
          "dort"
        ],
        "infinitive": [
          "machen"
        ]
      },
      "audioUrl": "/v1/audio/modal_verbs_B1_tier4/prompt-002.mp3"
    },
    {
      "id": "prompt-003",
      "text": "nächste Woche muss er bei Freunden essen.",
      "intent": "practice",
      "gloss_en": "I am practicing this grammar mechanic.",
      "natural_en": "nächste Woche muss er bei Freunden essen.",
      "slotsChanged": [
        "time",
        "subject",
        "verb",
        "location"
      ],
      "slots": {
        "subject": [
          "Er"
        ],
        "verb": [
          "muss"
        ],
        "time": [
          "nächste Woche"
        ],
        "location": [
          "bei Freunden"
        ],
        "infinitive": [
          "essen"
        ]
      },
      "audioUrl": "/v1/audio/modal_verbs_B1_tier4/prompt-003.mp3"
    },
    {
      "id": "prompt-004",
      "text": "am Wochenende soll er in der Stadt kaufen.",
      "intent": "practice",
      "gloss_en": "I am practicing this grammar mechanic.",
      "natural_en": "am Wochenende soll er in der Stadt kaufen.",
      "slotsChanged": [
        "subject",
        "verb",
        "time",
        "location"
      ],
      "slots": {
        "subject": [
          "Er"
        ],
        "verb": [
          "soll"
        ],
        "time": [
          "am Wochenende"
        ],
        "location": [
          "in der Stadt"
        ],
        "infinitive": [
          "kaufen"
        ]
      },
      "audioUrl": "/v1/audio/modal_verbs_B1_tier4/prompt-004.mp3"
    },
    {
      "id": "prompt-005",
      "text": "nächste Woche möchtet ihr dort ins Kino trinken.",
      "intent": "practice",
      "gloss_en": "I am practicing this grammar mechanic.",
      "natural_en": "nächste Woche möchtet ihr dort ins Kino trinken.",
      "slotsChanged": [
        "subject",
        "verb",
        "object",
        "time",
        "location"
      ],
      "slots": {
        "subject": [
          "Ihr"
        ],
        "verb": [
          "möchtet"
        ],
        "object": [
          "ins Kino"
        ],
        "time": [
          "nächste Woche"
        ],
        "location": [
          "dort"
        ],
        "infinitive": [
          "trinken"
        ]
      },
      "audioUrl": "/v1/audio/modal_verbs_B1_tier4/prompt-005.mp3"
    },
    {
      "id": "prompt-006",
      "text": "am Wochenende wollt ihr in der Stadt gehen.",
      "intent": "practice",
      "gloss_en": "I am practicing this grammar mechanic.",
      "natural_en": "am Wochenende wollt ihr in der Stadt gehen.",
      "slotsChanged": [
        "time",
        "subject",
        "verb",
        "location"
      ],
      "slots": {
        "subject": [
          "Ihr"
        ],
        "verb": [
          "wollt"
        ],
        "time": [
          "am Wochenende"
        ],
        "location": [
          "in der Stadt"
        ],
        "infinitive": [
          "gehen"
        ]
      },
      "audioUrl": "/v1/audio/modal_verbs_B1_tier4/prompt-006.mp3"
    },
    {
      "id": "prompt-007",
      "text": "nächste Woche möchte Sie in der Stadt hören.",
      "intent": "practice",
      "gloss_en": "I am practicing this grammar mechanic.",
      "natural_en": "nächste Woche möchte Sie in der Stadt hören.",
      "slotsChanged": [
        "subject",
        "verb",
        "time",
        "location"
      ],
      "slots": {
        "subject": [
          "Sie"
        ],
        "verb": [
          "möchte"
        ],
        "time": [
          "nächste Woche"
        ],
        "location": [
          "in der Stadt"
        ],
        "infinitive": [
          "hören"
        ]
      },
      "audioUrl": "/v1/audio/modal_verbs_B1_tier4/prompt-007.mp3"
    },
    {
      "id": "prompt-008",
      "text": "am Wochenende muss Sie im Büro ins Kino schlafen.",
      "intent": "practice",
      "gloss_en": "I am practicing this grammar mechanic.",
      "natural_en": "am Wochenende muss Sie im Büro ins Kino schlafen.",
      "slotsChanged": [
        "subject",
        "verb",
        "object",
        "time",
        "location"
      ],
      "slots": {
        "subject": [
          "Sie"
        ],
        "verb": [
          "muss"
        ],
        "object": [
          "ins Kino"
        ],
        "time": [
          "am Wochenende"
        ],
        "location": [
          "im Büro"
        ],
        "infinitive": [
          "schlafen"
        ]
      },
      "audioUrl": "/v1/audio/modal_verbs_B1_tier4/prompt-008.mp3"
    },
    {
      "id": "prompt-009",
      "text": "später will ich dort kommen.",
      "intent": "practice",
      "gloss_en": "I am practicing this grammar mechanic.",
      "natural_en": "später will ich dort kommen.",
      "slotsChanged": [
        "time",
        "subject",
        "verb",
        "location"
      ],
      "slots": {
        "subject": [
          "Ich"
        ],
        "verb": [
          "will"
        ],
        "time": [
          "später"
        ],
        "location": [
          "dort"
        ],
        "infinitive": [
          "kommen"
        ]
      },
      "audioUrl": "/v1/audio/modal_verbs_B1_tier4/prompt-009.mp3"
    },
    {
      "id": "prompt-010",
      "text": "heute möchte ich zu Hause sehen.",
      "intent": "practice",
      "gloss_en": "I am practicing this grammar mechanic.",
      "natural_en": "heute möchte ich zu Hause sehen.",
      "slotsChanged": [
        "subject",
        "verb",
        "time",
        "location"
      ],
      "slots": {
        "subject": [
          "Ich"
        ],
        "verb": [
          "möchte"
        ],
        "time": [
          "heute"
        ],
        "location": [
          "zu Hause"
        ],
        "infinitive": [
          "sehen"
        ]
      },
      "audioUrl": "/v1/audio/modal_verbs_B1_tier4/prompt-010.mp3"
    },
    {
      "id": "prompt-011",
      "text": "jetzt willst du dort zur Arbeit spielen.",
      "intent": "practice",
      "gloss_en": "I am practicing this grammar mechanic.",
      "natural_en": "jetzt willst du dort zur Arbeit spielen.",
      "slotsChanged": [
        "subject",
        "verb",
        "object",
        "time",
        "location"
      ],
      "slots": {
        "subject": [
          "Du"
        ],
        "verb": [
          "willst"
        ],
        "object": [
          "zur Arbeit"
        ],
        "time": [
          "jetzt"
        ],
        "location": [
          "dort"
        ],
        "infinitive": [
          "spielen"
        ]
      },
      "audioUrl": "/v1/audio/modal_verbs_B1_tier4/prompt-011.mp3"
    },
    {
      "id": "prompt-012",
      "text": "am Wochenende willst du zu Hause lernen.",
      "intent": "practice",
      "gloss_en": "I am practicing this grammar mechanic.",
      "natural_en": "am Wochenende willst du zu Hause lernen.",
      "slotsChanged": [
        "time",
        "subject",
        "verb",
        "location"
      ],
      "slots": {
        "subject": [
          "Du"
        ],
        "verb": [
          "willst"
        ],
        "time": [
          "am Wochenende"
        ],
        "location": [
          "zu Hause"
        ],
        "infinitive": [
          "lernen"
        ]
      },
      "audioUrl": "/v1/audio/modal_verbs_B1_tier4/prompt-012.mp3"
    }
  ],
  "analytics": {
    "version": 1,
    "mechanicId": "modal_verbs",
    "loopType": "pattern_switch",
    "targetStructures": [
      "modal_verb_infinitive",
      "modal_verb_requests",
      "modal_verb_ability"
    ],
    "variationSlots": [
      "subject",
      "verb"
    ],
    "coverage": {
      "verbs": [
        "können",
        "müssen",
        "muss",
        "soll",
        "möchtet",
        "wollt",
        "möchte",
        "will",
        "willst"
      ],
      "subjects": [
        "Wir",
        "Er",
        "Ihr",
        "Sie",
        "Ich",
        "Du"
      ],
      "patterns": [
        "modal_verb_infinitive",
        "modal_verb_requests",
        "modal_verb_ability"
      ]
    },
    "difficultyTier": 4,
    "recommendedReps": 4,
    "estPromptCount": 12,
    "timeboxMinutes": 5,
    "qualitySignals": {
      "tokenHitsCount": 12,
      "multiSlotRate": 1,
      "uniqueVerbCount": 9,
      "uniqueSubjectCount": 6,
      "trapPairCount": 0,
      "bannedPhraseCheckPassed": true
    }
  },
  "provenance": {
    "source": "template",
    "sourceRef": "mechanics/modal_verbs",
    "extractorVersion": "v4.0.0",
    "generatedAt": "2026-01-04T06:49:17.666Z"
  },
  "review": {
    "status": "needs_review"
  },
  "title_i18n": {
    "en": "Modal Verbs: B1 (Tier 4) - Pattern"
  },
  "shortTitle_i18n": {
    "en": "Modal Verbs B1 Pattern"
  },
  "subtitle_i18n": {
    "en": "Tier 4 - pattern switch - Practice modal verbs (können, müss"
  },
  "contentId": "de:drill:modal_verbs_b1_tier4_pattern-switch",
  "contentHash": "b2812fab299389216fe67c216b0f0863c1e7d3a85984218a697df49a33fde8fa",
  "revisionId": "b2812fab2993"
}
